turbofunc/__init__.py
turbofunc/clearprint.py
turbofunc/clearscreen.py
turbofunc/multiprint.py
turbofunc/pressanykey.py
turbofunc/sanitiseinput.py
turbofunc/standtextout.py
turbofunc-2.2.dist-info/LICENSE
turbofunc-2.2.dist-info/METADATA
turbofunc-2.2.dist-info/WHEEL
turbofunc-2.2.dist-info/top_level.txt
turbofunc-2.2.dist-info/RECORD
