Metadata-Version: 2.1
Name: turbofunc
Version: 2.2
Summary: simple functions for annoying-to-write tasks
Home-page: https://github.com/TheTechRobo/turbofunc
Author: TheTechRobo
Author-email: thetechrobo@pm.me
License: Apache 2.0
Project-URL: Source, https://github.com/thetechrobo/python-text-calculator
Project-URL: Tracker, https://github.com/thetechrobo/python-text-calculator/issues
Keywords: turbofunc,functions,press any key,getch,clear screen,easy,thetechrobo
Platform: UNKNOWN
Classifier: Development Status :: 5 - Production/Stable
Classifier: Intended Audience :: Developers
Classifier: Programming Language :: Python :: 3
Requires-Python: >=3.4
License-File: LICENSE
